CHANGES.txt
README.txt
setup.py
bda/__init__.py
bda.blogview.egg-info/PKG-INFO
bda.blogview.egg-info/SOURCES.txt
bda.blogview.egg-info/dependency_links.txt
bda.blogview.egg-info/entry_points.txt
bda.blogview.egg-info/namespace_packages.txt
bda.blogview.egg-info/not-zip-safe
bda.blogview.egg-info/requires.txt
bda.blogview.egg-info/top_level.txt
bda/blogview/__init__.py
bda/blogview/atiterator.py
bda/blogview/configure.zcml
bda/blogview/interfaces.py
bda/blogview/profiles.zcml
bda/blogview/skins.zcml
bda/blogview/browser/__init__.py
bda/blogview/browser/blog.py
bda/blogview/browser/blogkss.py
bda/blogview/browser/configure.zcml
bda/blogview/browser/interfaces.py
bda/blogview/browser/results.zcml
bda/blogview/browser/blogview/blog_entries_macro.pt
bda/blogview/browser/blogview/blog_view.pt
bda/blogview/browser/blogview/blog_view.pt.metadata
bda/blogview/browser/blogview/discussion_entry_macro.pt
bda/blogview/browser/blogview/discussion_reply.cpy
bda/blogview/browser/blogview/discussion_reply_form.cpt
bda/blogview/browser/blogview/discussion_reply_form.cpt.metadata
bda/blogview/browser/blogview/entry_threads_snippet.pt
bda/blogview/browser/css/blogview.css
bda/blogview/browser/images/close_comments.png
bda/blogview/browser/images/comment_arrow.png
bda/blogview/browser/images/open_comments.png
bda/blogview/browser/images/reply_arrow.png
bda/blogview/browser/js/blogview.js
bda/blogview/browser/js/blogviewkss.js
bda/blogview/browser/kss/blogview.kss
bda/blogview/browser/templates/blog_listing.pt
bda/blogview/browser/templates/blogkssview.pt
bda/blogview/browser/templates/threads.pt
bda/blogview/profiles/default/actions.xml
bda/blogview/profiles/default/cssregistry.xml
bda/blogview/profiles/default/jsregistry.xml
bda/blogview/profiles/default/kssregistry.xml
bda/blogview/profiles/default/skins.xml
bda/blogview/profiles/default/types.xml
bda/blogview/profiles/default/types/Folder.xml
bda/blogview/profiles/default/types/Plone_Site.xml
