Metadata-Version: 1.0
Name: bda.blogview
Version: 1.0-beta1
Summary: module providing a blog view for plone.
Home-page: UNKNOWN
Author: BlueDynamics Alliance
Author-email: dev@bluedynamics.com
License: GPL
Platform: UNKNOWN
Classifier: Development Status :: 4 - Beta
Classifier: Environment :: Web Environment
Classifier: Framework :: Zope2
Classifier: License :: OSI Approved :: GNU General Public License (GPL)
Classifier: Operating System :: OS Independent
Classifier: Programming Language :: Python
Classifier: Topic :: Internet :: WWW/HTTP :: Dynamic Content
